{
    "type": "FeatureCollection",
    "name": "Apotek",
    "crs": {
        "type": "name",
        "properties": {
            "name": "urn:ogc:def:crs:OGC:1.3:CRS84"
        }
    },
    "features": [
        {
            "type": "Feature",
            "properties": {
                "nama": "Apotek A'laddin Farma 1",
                "alamat": "Simpang Tiga Pasar Panimbang Kecamatan Panimbang"
            },
            "geometry": {
                "type": "Point",
                "coordinates": [
                    105.801148029939682,
                    -6.489903970672837
                ]
            }
        },
        {
            "type": "Feature",
            "properties": {
                "nama": "Apotik Central Farma",
                "alamat": "Jl. Nasional III, Panimbangjaya, Panimbang, Kabupaten Pandeglang"
            },
            "geometry": {
                "type": "Point",
                "coordinates": [
                    105.800834993647626,
                    -6.490605106259987
                ]
            }
        },
        {
            "type": "Feature",
            "properties": {
                "nama": "Apotik K76",
                "alamat": "Jl. Raya Tlk. Lada, Panimbangjaya, Panimbang, Kabupaten Pandeglang"
            },
            "geometry": {
                "type": "Point",
                "coordinates": [
                    105.802151470426566,
                    -6.490158330124601
                ]
            }
        },
        {
            "type": "Feature",
            "properties": {
                "nama": "Apotek Aladdin Farma 2",
                "alamat": "Jl. Nasional III, Panimbangjaya, Panimbang, Kabupaten Pandeglang"
            },
            "geometry": {
                "type": "Point",
                "coordinates": [
                    105.796313874150243,
                    -6.49330288765702
                ]
            }
        }
    ]
}